jwt_authenticator/__init__.py
jwt_authenticator/authenticator.py
authentication_app_psgrl-0.1.4.dist-info/METADATA
authentication_app_psgrl-0.1.4.dist-info/WHEEL
authentication_app_psgrl-0.1.4.dist-info/top_level.txt
authentication_app_psgrl-0.1.4.dist-info/RECORD
